checkpoint_api/__init__.py
checkpoint_api/checkpoint.py
checkpoint_api/enumerations.py
checkpoint_api/exceptions.py
tests/__init__.py
tests/test_login_logout.py
tests/test_misc.py
tests/test_search_object_by_cidr.py
checkpoint_api-0.1.8.dist-info/METADATA
checkpoint_api-0.1.8.dist-info/WHEEL
checkpoint_api-0.1.8.dist-info/top_level.txt
checkpoint_api-0.1.8.dist-info/RECORD
