Metadata-Version: 2.1
Name: checkpoint_api
Version: 0.1.8
Summary: Check Point REST API abstraction
Home-page: 
Author: Peter Gastinger
Author-email: peter.gastinger@gmail.com
Classifier: Programming Language :: Python :: 3
Classifier: Operating System :: OS Independent
Requires-Dist: requests
